README.rst
setup.py
php/__init__.py
php/test_php.py
php.egg-info/PKG-INFO
php.egg-info/SOURCES.txt
php.egg-info/dependency_links.txt
php.egg-info/top_level.txt