Metadata-Version: 1.2
Name: php
Version: 1.2.1
Summary: Handle some of the strange standards in PHP projects
Home-page: https://github.com/danielquinn/python-php
Author: Daniel Quinn
Author-email: code@danielquinn.org
Maintainer: Daniel Quinn
Maintainer-email: code@danielquinn.org
License: AGPLv3
Download-URL: https://github.com/danielquinn/python-php
Platform: UNKNOWN
Classifier: Operating System :: POSIX
Classifier: Operating System :: Unix
Classifier: Programming Language :: Python
Classifier: Programming Language :: Python :: 2.6
Classifier: Programming Language :: Python :: 2.7
Classifier: Programming Language :: Python :: 3.1
Classifier: Programming Language :: Python :: 3.2
Classifier: Programming Language :: Python :: 3.3
Classifier: Programming Language :: PHP
Classifier: Topic :: Internet :: WWW/HTTP
